[
    {
        "id": 1,
        "name": "BHH T-shirt in grün",
        "choosedSize": "",
        "color": "Blau",
        "preis": "25€",
        "url":"../src/assets/t-shirtBlau.jpg"
    },
    {
        "id": 2,
        "name": "BHH T-shirt in DunkelGrün  ",
        "choosedSize": "",
        "color": "Dunkel Grün",
        "preis": "59,99€",
        "url":"../src/assets/t-shirtDunkelGrün.jpg"

        
    },
    {
        "id": 3,
        "name": "BHH T-shirt",
        "choosedSize": "",
        "color": "Gelb",
        "preis": "39,99€",
        "url":"../src/assets/gelb.jpg"
    },
    {
        "id": 4,
        "name": "BHH T-Shirt",
        "choosedSize": "",
        "color": "Blau",
        "preis": "15,99€",
        "url":"../src/assets/babyblau.jpg"
    },
    {
        "id": 5,
        "name": "BHH Rot Hoodie ",
        "choosedSize": "",
        "color": "Rot",
        "preis": "59,99€",
        "url":"../src/assets/hoodieweinrot.jpg"
    },
    {
        "id": 6,
        "name": "BHH White Hoodie",
        "choosedSize": "",
        "color": "Weiß",
        "preis": "59,99€",
        "url":"../src/assets/hoodieweiß.jpg"
    },
    {
        "id": 7,
        "name": "BHH Black Hoodie",
        "choosedSize": "",
        "color": "Black",
        "preis": "35,45€",
        "url":"../src/assets/hoodieschwarz.jpg"
    },
    {
        "id": 8,
        "name": "BHH Blue Polo",
        "choosedSize": "",
        "color": "Blau",
        "preis": "59,99€",
        "url":"../src/assets/poloblau.jpg"
    },
    {
        "id": 8,
        "name": "BHH White Polo",
        "choosedSize": "",
        "color": "Weiß",
        "preis": "59,99€",
        "url":"../src/assets/poloweiß.jpg"
    }
]